elytica_dss/__init__.py
elytica_dss/application.py
elytica_dss/inputfile.py
elytica_dss/job.py
elytica_dss/outputfile.py
elytica_dss/project.py
elytica_dss/service.py
elytica_dss/user.py
elytica_dss-2.0.1.dist-info/METADATA
elytica_dss-2.0.1.dist-info/WHEEL
elytica_dss-2.0.1.dist-info/top_level.txt
elytica_dss-2.0.1.dist-info/RECORD
