Metadata-Version: 2.1
Name: elytica-dss
Version: 2.0.1
Summary: Package for elytica service we use to build decision support systems (DSSs).
Home-page: https://github.com/baggins800/elytica-dss
Author: Ruan Luies
Author-email: ruan@elytica.com
License: GPL
Keywords: DSS,decision,support,system,mixed,integer,linear,programming
Platform: UNKNOWN
Classifier: Development Status :: 3 - Alpha
Classifier: Intended Audience :: Developers
Classifier: Topic :: Software Development :: Build Tools
Requires-Dist: requests (>=1.6)
Requires-Dist: setuptools-git-versioning
Requires-Dist: websocket-client (==0.57.0)
Requires-Dist: elytica-pysher (==1.0.7)
